fan_manager/__init__.py
fan_manager/__main__.py
fan_manager/fan_manager.py
fan_manager/fan_manager_mcp.py
fan_manager-1.0.6.dist-info/licenses/LICENSE
fan_manager-1.0.6.dist-info/METADATA
fan_manager-1.0.6.dist-info/WHEEL
fan_manager-1.0.6.dist-info/entry_points.txt
fan_manager-1.0.6.dist-info/top_level.txt
fan_manager-1.0.6.dist-info/RECORD
