Metadata-Version: 2.4
Name: fan-manager
Version: 1.0.6
Summary: Manager your Dell PowerEdge Fan Speed with this handy tool and MCP Server!
Author-email: Audel Rouhi <knucklessg1@gmail.com>
License: MIT
Classifier: Development Status :: 5 - Production/Stable
Classifier: License :: Public Domain
Classifier: Environment :: Console
Classifier: Operating System :: POSIX :: Linux
Classifier: Programming Language :: Python :: 3
Requires-Python: >=3.8
License-File: LICENSE
Requires-Dist: fastmcp>=2.12.4
Dynamic: license-file
